LICENSE.txt
MANIFEST.in
README.md
pyproject.toml
setup.cfg
setup.py
versioneer.py
mitype/__init__.py
mitype/__main__.py
mitype/_version.py
mitype/app.py
mitype/calculations.py
mitype/commandline.py
mitype/data.db
mitype/database.py
mitype/history.py
mitype/keycheck.py
mitype/signals.py
mitype/timer.py
mitype.egg-info/PKG-INFO
mitype.egg-info/SOURCES.txt
mitype.egg-info/dependency_links.txt
mitype.egg-info/entry_points.txt
mitype.egg-info/not-zip-safe
mitype.egg-info/requires.txt
mitype.egg-info/top_level.txt
tests/test_history.py
tests/test_typing.py