Metadata-Version: 2.1
Name: mitype
Version: 0.2.5
Summary: A command line tool to improve typing speed
Home-page: https://github.com/mithil467/mitype
Download-URL: https://github.com/mithil467/mitype/archive/v0.2.5.tar.gz
Author: MITHIL POOJARY
Author-email: mithil467@gmail.com
License: GPL
Keywords: MITYPE,TERMINAL,WPM,SPEED,TYPE
Classifier: Development Status :: 5 - Production/Stable
Classifier: Intended Audience :: Developers
Classifier: Intended Audience :: End Users/Desktop
Classifier: License :: OSI Approved :: GNU General Public License v3 (GPLv3)
Classifier: Environment :: Console
Classifier: Natural Language :: English
Classifier: Topic :: Terminals
Classifier: Topic :: Games/Entertainment
Classifier: Operating System :: OS Independent
Classifier: Programming Language :: Python
Classifier: Programming Language :: Python :: 3
Classifier: Programming Language :: Python :: 3.6
Classifier: Programming Language :: Python :: 3.7
Classifier: Programming Language :: Python :: 3.8
Classifier: Programming Language :: Python :: 3.9
Classifier: Programming Language :: Python :: 3.10
Classifier: Programming Language :: Python :: 3 :: Only
License-File: LICENSE.txt
Requires-Dist: windows-curses==2.3.0; platform_system == "Windows"
Provides-Extra: dev
Requires-Dist: pytest; extra == "dev"
